swancustomenvironments/__init__.py
swancustomenvironments/_version.py
swancustomenvironments/serverextension.py
swancustomenvironments/scripts/makenv.sh
swancustomenvironments/scripts/builders/accpy.sh
swancustomenvironments/scripts/builders/mamba.sh
swancustomenvironments/scripts/builders/venv.sh
swancustomenvironments/templates/customenvs.html
swancustomenvironments-0.0.31.data/data/etc/jupyter/jupyter_server_config.d/swancustomenvironments.json
swancustomenvironments-0.0.31.data/data/share/jupyter/labextensions/swancustomenvironments/package.json
swancustomenvironments-0.0.31.data/data/share/jupyter/labextensions/swancustomenvironments/static/509.0a3cfbae887c5afd9734.js
swancustomenvironments-0.0.31.data/data/share/jupyter/labextensions/swancustomenvironments/static/728.0c2255a1c6508192dbe7.js
swancustomenvironments-0.0.31.data/data/share/jupyter/labextensions/swancustomenvironments/static/remoteEntry.733fb6d23deea60ae621.js
swancustomenvironments-0.0.31.data/data/share/jupyter/labextensions/swancustomenvironments/static/style.js
swancustomenvironments-0.0.31.data/data/share/jupyter/labextensions/swancustomenvironments/static/third-party-licenses.json
swancustomenvironments-0.0.31.data/data/share/jupyter/labextensions/swancustomenvironments/install.json
swancustomenvironments-0.0.31.dist-info/METADATA
swancustomenvironments-0.0.31.dist-info/WHEEL
swancustomenvironments-0.0.31.dist-info/licenses/LICENSE
swancustomenvironments-0.0.31.dist-info/RECORD
