Metadata-Version: 2.4
Name: swancustomenvironments
Version: 0.0.31
Dynamic: Keywords
Summary: Extension to provide support for venvs
Project-URL: Homepage, https://github.com/swan-cern/jupyter-extensions
Project-URL: Bug Tracker, https://github.com/swan-cern/jupyter-extensions/issues
Project-URL: Repository, https://github.com/swan-cern/jupyter-extensions.git
Author: SWAN Team
License:                     GNU AFFERO GENERAL PUBLIC LICENSE
License-File: LICENSE
Classifier: Framework :: Jupyter
Classifier: Framework :: Jupyter :: JupyterLab
Classifier: Framework :: Jupyter :: JupyterLab :: 4
Classifier: Framework :: Jupyter :: JupyterLab :: Extensions
Classifier: Framework :: Jupyter :: JupyterLab :: Extensions :: Prebuilt
Classifier: License :: OSI Approved :: BSD License
Classifier: Programming Language :: Python
Classifier: Programming Language :: Python :: 3
Classifier: Programming Language :: Python :: 3.8
Classifier: Programming Language :: Python :: 3.9
Classifier: Programming Language :: Python :: 3.10
Classifier: Programming Language :: Python :: 3.11
Classifier: Programming Language :: Python :: 3.12
Requires-Python: >=3.8
Requires-Dist: jupyter-server<3,>=2.0.1
